pavlov/__init__.py
pavlov/pavlov.py
async_pavlov-0.4.0.dist-info/LICENSE
async_pavlov-0.4.0.dist-info/WHEEL
async_pavlov-0.4.0.dist-info/METADATA
async_pavlov-0.4.0.dist-info/RECORD
